LICENSE
MANIFEST.in
README.md
setup.py
serf_master/__init__.py
serf_master.egg-info/PKG-INFO
serf_master.egg-info/SOURCES.txt
serf_master.egg-info/dependency_links.txt
serf_master.egg-info/not-zip-safe
serf_master.egg-info/top_level.txt