Metadata-Version: 1.1
Name: serf-master
Version: 0.4
Summary: helpers for writing manageable Serf handlers
Home-page: http://github.com/garethr/serf-master
Author: Gareth Rushgrove
Author-email: gareth@morethanseven.net
License: MIT
Keywords: serf
Platform: UNKNOWN
Classifier: Development Status :: 3 - Alpha
Classifier: Intended Audience :: Developers
Classifier: License :: OSI Approved :: MIT License
Classifier: Natural Language :: English
Classifier: Topic :: System :: Systems Administration
